Metadata-Version: 2.4
Name: objwatch
Version: 0.5.1
Summary: A Python library to trace and monitor object attributes and method calls.
Home-page: https://github.com/aeeeeeep/objwatch
Author: aeeeeeep
Author-email: aeeeeeep <aeeeeeep@proton.me>
Project-URL: Homepage, https://github.com/aeeeeeep/objwatch
Project-URL: Documentation, https://objwatch.readthedocs.io
Project-URL: Repository, https://github.com/aeeeeeep/objwatch
Project-URL: Bug Tracker, https://github.com/aeeeeeep/objwatch/issues
Classifier: Operating System :: OS Independent
Classifier: Programming Language :: Python :: 3.8
Classifier: Programming Language :: Python :: 3.9
Classifier: Programming Language :: Python :: 3.10
Classifier: Programming Language :: Python :: 3.11
Classifier: Programming Language :: Python :: 3.12
Classifier: Programming Language :: Python :: 3.13
Classifier: Programming Language :: Python :: 3.14
Classifier: Programming Language :: Python :: 3.15
Requires-Python: >=3.8,<3.16
License-File: LICENSE
Requires-Dist: psutil
Dynamic: author
Dynamic: home-page
Dynamic: license-file
Dynamic: requires-python
